ogn_lib/__init__.py
ogn_lib/client.py
ogn_lib/constants.py
ogn_lib/exceptions.py
ogn_lib/parser.py
ogn_lib-0.2.5.dist-info/DESCRIPTION.rst
ogn_lib-0.2.5.dist-info/METADATA
ogn_lib-0.2.5.dist-info/RECORD
ogn_lib-0.2.5.dist-info/WHEEL
ogn_lib-0.2.5.dist-info/metadata.json
ogn_lib-0.2.5.dist-info/top_level.txt
