Metadata-Version: 2.0
Name: ogn-lib
Version: 0.2.5
Summary: Beacon processor for the OGN data stream.
Home-page: https://github.com/akolar/ogn-lib
Author: Anze Kolar
Author-email: me@akolar.com
License: MIT
Download-URL: https://github.com/akolar/ogn-lib
Platform: UNKNOWN
Classifier: Development Status :: 3 - Alpha
Classifier: Intended Audience :: Developers
Classifier: License :: OSI Approved :: MIT License
Classifier: Programming Language :: Python :: 3.4
Classifier: Programming Language :: Python :: 3.5
Classifier: Programming Language :: Python :: 3.6
Classifier: Programming Language :: Python :: 3.7
Classifier: Programming Language :: Python :: 3 :: Only
Classifier: Topic :: Utilities
